lsst/__init__.py
lsst/sdm/__init__.py
lsst/sdm/schemas/__init__.py
lsst/sdm/schemas/apdb.yaml
lsst/sdm/schemas/cdb_latiss.yaml
lsst/sdm/schemas/cdb_lsstcam.yaml
lsst/sdm/schemas/cdb_lsstcomcam.yaml
lsst/sdm/schemas/cdb_lsstcomcamsim.yaml
lsst/sdm/schemas/cdb_startrackerfast.yaml
lsst/sdm/schemas/cdb_startrackernarrow.yaml
lsst/sdm/schemas/cdb_startrackerwide.yaml
lsst/sdm/schemas/dp02_dc2.yaml
lsst/sdm/schemas/dp02_obscore.yaml
lsst/sdm/schemas/dp03_10yr.yaml
lsst/sdm/schemas/dp03_1yr.yaml
lsst/sdm/schemas/dp1.yaml
lsst/sdm/schemas/efd_latiss.yaml
lsst/sdm/schemas/efd_lsstcam.yaml
lsst/sdm/schemas/efd_lsstcomcam.yaml
lsst/sdm/schemas/hsc.yaml
lsst/sdm/schemas/imsim.yaml
lsst/sdm/schemas/ivoa_obscore.yaml
lsst/sdm/schemas/lsstcam.yaml
lsst/sdm/schemas/obsloctap.yaml
lsst/sdm/schemas/oga_live_obscore.yaml
lsst/sdm/schemas/archive/baselineSchema.yaml
lsst/sdm/schemas/archive/dp01_dc2.yaml
lsst/sdm/schemas/ivoa/make_obscore_nominal.py
lsst/sdm/schemas/ivoa/obscore_nominal.yaml
lsst_sdm_schemas-30.2026.400.dist-info/licenses/COPYRIGHT
lsst_sdm_schemas-30.2026.400.dist-info/licenses/LICENSE
lsst_sdm_schemas-30.2026.400.dist-info/METADATA
lsst_sdm_schemas-30.2026.400.dist-info/WHEEL
lsst_sdm_schemas-30.2026.400.dist-info/top_level.txt
lsst_sdm_schemas-30.2026.400.dist-info/zip-safe
lsst_sdm_schemas-30.2026.400.dist-info/RECORD
