Metadata-Version: 2.4
Name: lsst-sdm-schemas
Version: 30.2026.400
Summary: Science Data Model (SDM) Schemas for Rubin Observatory
Author-email: Rubin Observatory Data Management <dm-admin@lists.lsst.org>
License-Expression: GPL-3.0-or-later
Project-URL: Homepage, https://sdm-schemas.lsst.io
Project-URL: Source, https://github.com/lsst/sdm_schemas
Keywords: lsst
Classifier: Intended Audience :: Science/Research
Classifier: Operating System :: OS Independent
Classifier: Programming Language :: Python :: 3
Classifier: Programming Language :: Python :: 3.11
Classifier: Programming Language :: Python :: 3.12
Classifier: Programming Language :: Python :: 3.13
Classifier: Topic :: Scientific/Engineering :: Astronomy
Requires-Python: >=3.11.0
License-File: COPYRIGHT
License-File: LICENSE
Requires-Dist: lsst-felis
Provides-Extra: test
Requires-Dist: pytest>=3.2; extra == "test"
Dynamic: license-file
